{
"type": "FeatureCollection",
"name": "Pharmacies",
"crs": { "type": "name", "properties": { "name": "urn:ogc:def:crs:OGC:1.3:CRS84" } },
"features": [
{ "type": "Feature", "properties": { "Noms": "PHARMACIE SAMBA", "Type": "Pharmacie", "Téléphone": null, "X": 11.1487734, "Y": 2.9101999, "layer": "pharmacies", "path": "D:\/NIVEAU 5\/WEBMAPPING\/cc webmapping\/pharmacies.kml|layername=pharmacies" }, "geometry": { "type": "Point", "coordinates": [ 11.1487734, 2.9101999 ] } },
{ "type": "Feature", "properties": { "Noms": "PHARMACIE DE LA RENAISSANCE", "Type": "Pharmacie", "Téléphone": null, "X": 11.1549415, "Y": 2.9240781, "layer": "pharmacies", "path": "D:\/NIVEAU 5\/WEBMAPPING\/cc webmapping\/pharmacies.kml|layername=pharmacies" }, "geometry": { "type": "Point", "coordinates": [ 11.1549415, 2.9240781 ] } },
{ "type": "Feature", "properties": { "Noms": "Pharmacie la Mvila", "Type": "Pharmacie", "Téléphone": null, "X": 11.1513157, "Y": 2.9193027, "layer": "pharmacies", "path": "D:\/NIVEAU 5\/WEBMAPPING\/cc webmapping\/pharmacies.kml|layername=pharmacies" }, "geometry": { "type": "Point", "coordinates": [ 11.1513157, 2.9193027 ] } },
{ "type": "Feature", "properties": { "Noms": "pharmacie du bercail", "Type": "Pharmacie", "Téléphone": null, "X": 11.1508853, "Y": 2.9207702, "layer": "pharmacies", "path": "D:\/NIVEAU 5\/WEBMAPPING\/cc webmapping\/pharmacies.kml|layername=pharmacies" }, "geometry": { "type": "Point", "coordinates": [ 11.1508853, 2.9207702 ] } }
]
}
