{
  "type": "FeatureCollection",
  "generator": "overpass-turbo",
  "copyright": "The data included in this document is from www.openstreetmap.org. The data is made available under ODbL.",
  "timestamp": "2025-05-14T14:52:15Z",
  "features": [
    {
      "type": "Feature",
      "properties": {
        "@id": "node/11469840173",
        "amenity": "college",
        "check_date": "2023-12-30",
        "name": "École Technique D’Agriculture ETA D’Ebolowa",
        "note": "OSM ENSTP",
        "phone": "+237 2 22 28 31 59",
        "source": "survey"
      },
      "geometry": {
        "type": "Point",
        "coordinates": [
          11.1515119,
          2.9277733
        ]
      },
      "id": "node/11469840173"
    },
    {
      "type": "Feature",
      "properties": {
        "@id": "node/11469993918",
        "amenity": "college",
        "check_date": "2023-12-30",
        "name": "Facultés Des Sciences Juridiques Et Politiques Université D’Ebolowa"
      },
      "geometry": {
        "type": "Point",
        "coordinates": [
          11.1649797,
          2.9190687
        ]
      },
      "id": "node/11469993918"
    }
  ]
}