{
  "type": "FeatureCollection",
  "generator": "overpass-turbo",
  "copyright": "The data included in this document is from www.openstreetmap.org. The data is made available under ODbL.",
  "timestamp": "2025-05-14T14:53:15Z",
  "features": [
    {
      "type": "Feature",
      "properties": {
        "@id": "node/11469866823",
        "amenity": "university",
        "check_date": "2023-12-30",
        "name": "Décanat Faculté Des Sciences Université D’Ebolowa"
      },
      "geometry": {
        "type": "Point",
        "coordinates": [
          11.1547476,
          2.9272113
        ]
      },
      "id": "node/11469866823"
    },
    {
      "type": "Feature",
      "properties": {
        "@id": "node/11472952276",
        "amenity": "university",
        "check_date": "2024-01-01",
        "name": "Faculté des Sciences économiques et de gestion",
        "note": "OSM ENSTP",
        "operator:type": "public",
        "source": "survey",
        "survey:date": "2023-12-31"
      },
      "geometry": {
        "type": "Point",
        "coordinates": [
          11.1403424,
          2.9116157
        ]
      },
      "id": "node/11472952276"
    }
  ]
}