{
"type": "FeatureCollection",
"name": "Communauté urbaine",
"crs": { "type": "name", "properties": { "name": "urn:ogc:def:crs:OGC:1.3:CRS84" } },
"features": [
{ "type": "Feature", "properties": { "Noms": "Communaute Urbaine", "Quartier": null, "Accessibilité": null, "X": null, "Y": null, "layer": "Communauté urbaine", "path": "D:\\NIVEAU 5\\WEBMAPPING\\cc webmapping\\Services ADMINIST.kml|layername=Services ADMINIST" }, "geometry": { "type": "Point", "coordinates": [ 11.1798773, 2.9125333 ] } }
]
}
